gcutils/__init__.py
gcutils/datastore.py
gcutils/exceptions.py
gcutils/storage.py
bxdx_gcutils-0.1.0.dist-info/METADATA
bxdx_gcutils-0.1.0.dist-info/WHEEL
bxdx_gcutils-0.1.0.dist-info/RECORD
