Metadata-Version: 2.1
Name: bxdx-gcutils
Version: 0.1.0
Summary: Utility functions to interact with Google Cloud
Author: Benjamin Labrecque
Requires-Python: >=3.8,<4.0
Classifier: Programming Language :: Python :: 3
Classifier: Programming Language :: Python :: 3.8
Classifier: Programming Language :: Python :: 3.9
Classifier: Programming Language :: Python :: 3.10
Classifier: Programming Language :: Python :: 3.11
Classifier: Programming Language :: Python :: 3.12
Requires-Dist: google-cloud-datastore (>=2.19.0,<3.0.0)
Requires-Dist: google-cloud-storage (>=2.14.0,<3.0.0)
Requires-Dist: pydantic (>=2.0.0,<3.0.0)
Requires-Dist: tenacity (>=8.2.3,<9.0.0)
